finam_mhm/__init__.py
finam_mhm/_version.py
finam_mhm/component.py
finam_mhm/constants.py
finam_mhm-0.2.0.dist-info/METADATA
finam_mhm-0.2.0.dist-info/WHEEL
finam_mhm-0.2.0.dist-info/licenses/AUTHORS.md
finam_mhm-0.2.0.dist-info/licenses/COPYING
finam_mhm-0.2.0.dist-info/licenses/COPYING.LESSER
finam_mhm-0.2.0.dist-info/licenses/LICENSE.md
finam_mhm-0.2.0.dist-info/RECORD
